{
    "properties": {},
    "type": "Feature",
    "geometry": {
        "type": "Polygon",
        "coordinates": [
            [
                [
                    175.2847623825073,
                    -37.77495501866911
                ],
                [
                    175.2933883666992,
                    -37.77298755890846
                ],
                [
                    175.29175758361816,
                    -37.779398571318765
                ],
                [
                    175.28845310211182,
                    -37.78075532805877
                ],
                [
                    175.2847623825073,
                    -37.77495501866911
                ]
            ]
        ]
    }
}
